bit8/__init__.py
bit8/bit8.py
bit8/bsl.py
bit8/bw.py
bit8/game.py
bit8/utils.py
bit8-0.0.3.dist-info/LICENSE
bit8-0.0.3.dist-info/WHEEL
bit8-0.0.3.dist-info/METADATA
bit8-0.0.3.dist-info/RECORD
