Metadata-Version: 2.1
Name: bit8
Version: 0.0.3
Summary: Simple terminal game engine
Author-email: Pradhyum Rajasekar <techieji2017@outlook.com>
Classifier: License :: OSI Approved :: MIT License
Project-URL: Home, https://github.com/techieji/bit8
